AUTHORS
LICENSE
MANIFEST.in
requirements.txt
setup.py
hedwig/__init__.py
hedwig/utils.py
hedwig/core/__init__.py
hedwig/core/base.py
hedwig/core/consumer.py
hedwig/core/emitter.py
hedwig/core/exceptions.py
hedwig/core/service.py
hedwig/core/settings.py
hedwig/core/worker.py
hedwig/django/__init__.py
hedwig/django/apps.py
hedwig/django/emitter.py
hedwig/django/run.py
hedwig/django/settings.py
hedwig/django/signals.py
hedwig/django/views.py
hedwig/django/worker.py
hedwig/rest_framework/__init__.py
hedwig/rest_framework/apps.py
hedwig/rest_framework/serializers.py
hedwig/rest_framework/settings.py
hedwig_py.egg-info/PKG-INFO
hedwig_py.egg-info/SOURCES.txt
hedwig_py.egg-info/dependency_links.txt
hedwig_py.egg-info/not-zip-safe
hedwig_py.egg-info/requires.txt
hedwig_py.egg-info/top_level.txt