Metadata-Version: 1.1
Name: hedwig-py
Version: 0.1.9
Summary: Python emitter and consumer for Hedwig
Home-page: https://github.com/ofpiyush/hedwig-py/
Author: Piyush
Author-email: mail@ofpiyush.in
License: MIT
Platform: UNKNOWN
Classifier: Development Status :: 3 - Alpha
Classifier: Intended Audience :: Developers
Classifier: License :: OSI Approved :: MIT License
Classifier: Operating System :: OS Independent
Classifier: Topic :: System :: Distributed Computing
